mkdocs_glossary/__init__.py
mkdocs_glossary/plugin.py
mkdocs_glossary-0.1.5.dist-info/METADATA
mkdocs_glossary-0.1.5.dist-info/WHEEL
mkdocs_glossary-0.1.5.dist-info/entry_points.txt
mkdocs_glossary-0.1.5.dist-info/top_level.txt
mkdocs_glossary-0.1.5.dist-info/RECORD
