Metadata-Version: 2.1
Name: mkdocs-glossary
Version: 0.1.5
Summary: A MkDocs plugin that automatically creates references to glossary terms within italicized text from a specified glossary list file.
Home-page: https://gitlab.com/thiti-mkdocs-plugins/mkdocs-glossary
Author: Thibaud Briard
Author-email: thiti517@outlook.com
License: MIT
Keywords: mkdocs
Platform: UNKNOWN
Classifier: Development Status :: 3 - Alpha
Classifier: Intended Audience :: Developers
Classifier: Intended Audience :: Education
Classifier: License :: OSI Approved :: MIT License
Classifier: Programming Language :: Python
Classifier: Programming Language :: Python :: 3 :: Only
Requires-Python: >=3.8
Requires-Dist: mkdocs (>=1.4.2)
